pulser_simulation/__init__.py
pulser_simulation/_version.py
pulser_simulation/hamiltonian.py
pulser_simulation/py.typed
pulser_simulation/qutip_backend.py
pulser_simulation/qutip_config.py
pulser_simulation/qutip_op.py
pulser_simulation/qutip_result.py
pulser_simulation/qutip_state.py
pulser_simulation/simconfig.py
pulser_simulation/simresults.py
pulser_simulation/simulation.py
pulser_simulation-1.6.3.dist-info/licenses/LICENSE
pulser_simulation-1.6.3.dist-info/METADATA
pulser_simulation-1.6.3.dist-info/WHEEL
pulser_simulation-1.6.3.dist-info/top_level.txt
pulser_simulation-1.6.3.dist-info/RECORD
