Metadata-Version: 2.4
Name: pulser-simulation
Version: 1.6.3
Summary: An emulator of pulse-level sequences created with Pulser.
Home-page: https://github.com/pasqal-io/Pulser
Author: Pulser Development Team
License: Apache 2.0
Classifier: Development Status :: 5 - Production/Stable
Classifier: Programming Language :: Python :: 3
Requires-Python: >=3.9
License-File: LICENSE
Requires-Dist: qutip<6,>=5
Requires-Dist: pulser-core==1.6.3
Dynamic: author
Dynamic: classifier
Dynamic: description
Dynamic: description-content-type
Dynamic: home-page
Dynamic: license
Dynamic: license-file
Dynamic: requires-dist
Dynamic: requires-python
Dynamic: summary
